secure_config_loader/__init__.py
secure_config_loader/core.py
secure_config_loader-0.1.4.dist-info/METADATA
secure_config_loader-0.1.4.dist-info/WHEEL
secure_config_loader-0.1.4.dist-info/top_level.txt
secure_config_loader-0.1.4.dist-info/RECORD
