Metadata-Version: 2.4
Name: secure-config-loader
Version: 0.1.4
Summary: Secure multi-format configuration loader with Ansible Vault support
Home-page: https://github.com/aiziyuer/secure-config-loader
Author: aiziyuer
Author-email: 910217951@qq.com
Classifier: Development Status :: 4 - Beta
Classifier: Intended Audience :: Developers
Classifier: License :: OSI Approved :: MIT License
Classifier: Programming Language :: Python :: 3.10
Classifier: Operating System :: OS Independent
Requires-Python: >=3.10
Requires-Dist: ansible-core>=2.13
Requires-Dist: python-box>=6.0
Requires-Dist: PyYAML>=6.0
Requires-Dist: toml>=0.10
Requires-Dist: python-box>=7.2.0
Requires-Dist: python-dotenv>=0.19
Dynamic: author
Dynamic: author-email
Dynamic: classifier
Dynamic: description
Dynamic: description-content-type
Dynamic: home-page
Dynamic: requires-dist
Dynamic: requires-python
Dynamic: summary
